{"security": {"id": 136, "market_id": 4, "symbol": "CNERGY", "provider_symbol": "CNERGY.KA", "name": null, "asset_class": "equity", "sector": null, "industry": null, "currency": "PKR", "country": "PK", "isin": null, "figi": null, "cik": null, "market_cap": null, "shares_outstanding": null, "is_active": true, "market_code": "PSX", "region": "psx"}, "tradingview_symbol": null, "quote": null, "scores": {"id": 95, "security_id": 136, "as_of": "2026-07-24", "fundamental": 47.99, "technical": null, "momentum": null, "quality": 40.07, "risk": 56.48, "composite": 48.09, "breakdown": {"fundamental": {"score": 47.99, "coverage": 1.0, "weight_present": 1.0, "metrics": {"roe": {"label": "Return on equity", "value": 0.069957, "sub_score": 27.98, "weight": 0.14, "contribution": 3.9172}, "net_margin": {"label": "Net margin", "value": 0.044882, "sub_score": 22.44, "weight": 0.1, "contribution": 2.244}, "roa": {"label": "Return on assets", "value": 0.035119, "sub_score": 29.27, "weight": 0.08, "contribution": 2.3416}, "gross_margin": {"label": "Gross margin", "value": 0.079312, "sub_score": 13.22, "weight": 0.06, "contribution": 0.7932}, "revenue_growth": {"label": "Revenue growth", "value": 0.118732, "sub_score": 62.49, "weight": 0.1, "contribution": 6.249}, "eps_growth": {"label": "EPS growth", "value": 23.916667, "sub_score": 100.0, "weight": 0.1, "contribution": 10.0}, "debt_to_equity": {"label": "Debt / equity", "value": 0.079432, "sub_score": 96.82, "weight": 0.1, "contribution": 9.682}, "current_ratio": {"label": "Current ratio", "value": 0.917003, "sub_score": 41.7, "weight": 0.06, "contribution": 2.502}, "interest_coverage": {"label": "Interest coverage", "value": 6.961527, "sub_score": 66.24, "weight": 0.06, "contribution": 3.9744}, "fcf_margin": {"label": "Free-cash-flow margin", "value": 0.028586, "sub_score": 19.06, "weight": 0.05, "contribution": 0.953}, "piotroski_f": {"label": "Piotroski F-Score", "value": 6.0, "sub_score": 66.67, "weight": 0.08, "contribution": 5.3336}, "altman_z": {"label": "Altman Z-Score", "value": 1.379709, "sub_score": 0.0, "weight": 0.07, "contribution": 0.0}}, "missing": [], "piotroski_criteria": {"positive_roa": true, "positive_ocf": true, "roa_improved": true, "accruals": false, "lower_leverage": true, "higher_current_ratio": true, "no_dilution": false, "higher_margin": true, "higher_turnover": false}}, "composite": {"composite": 48.09, "coverage": 0.55, "weights": {"fundamental": 0.35, "technical": 0.35, "momentum": 0.1, "quality": 0.1, "risk": 0.1}, "components": {"fundamental": {"score": 47.99, "weight": 0.35, "contribution": 30.54}, "quality": {"score": 40.07, "weight": 0.1, "contribution": 7.29}, "risk": {"score": 56.48, "weight": 0.1, "contribution": 10.27}}, "dimensions": {"momentum": {"reason": "no_technical_indicators"}, "quality": {"metrics": {"roe": {"label": "Return on equity", "value": 0.069957, "sub_score": 27.98, "weight": 0.25, "contribution": 6.995}, "net_margin": {"label": "Net margin", "value": 0.044882, "sub_score": 22.44, "weight": 0.2, "contribution": 4.488}, "gross_margin": {"label": "Gross margin", "value": 0.079312, "sub_score": 13.22, "weight": 0.15, "contribution": 1.983}, "piotroski_f": {"label": "Piotroski F-Score", "value": 6.0, "sub_score": 66.67, "weight": 0.25, "contribution": 16.6675}, "interest_coverage": {"label": "Interest coverage", "value": 6.961527, "sub_score": 66.24, "weight": 0.15, "contribution": 9.936}}, "missing": [], "coverage": 1.0}, "risk": {"metrics": {"debt_to_equity": {"label": "Debt / equity", "value": 0.079432, "sub_score": 96.82, "weight": 0.35, "contribution": 33.887}, "altman_z": {"label": "Altman Z-Score", "value": 1.379709, "sub_score": 0.0, "weight": 0.25, "contribution": 0.0}}, "missing": ["volatility"], "coverage": 0.6}}}}}, "signal": {"id": 98, "security_id": 136, "as_of": "2026-07-24", "signal_type": "hold", "confidence": 0.398, "rationale": "Composite 48/100 \u2192 Hold. Top drivers: risk 56, fundamental 48, quality 40.", "triggers": {"fundamental": 47.99, "quality": 40.07, "risk": 56.48}, "label": "Hold"}, "fundamentals": {"security_id": 136, "as_of": "2026-03-31", "pe_ttm": null, "roe": 0.069957, "debt_to_equity": 0.079432, "revenue_growth": 0.118732, "eps_growth": 23.916667, "net_margin": 0.044882, "dividend_yield": null, "market_cap": null}, "ratios": {"id": 95, "security_id": 136, "period": "annual", "fiscal_date": "2026-03-31", "gross_margin": 0.079312, "operating_margin": 0.071207, "net_margin": 0.044882, "roe": 0.069957, "roa": 0.035119, "roic": 0.072933, "revenue_growth": 0.118732, "revenue_cagr_3y": 0.194246, "eps_growth": 23.916667, "eps_cagr_3y": null, "debt_to_equity": 0.079432, "current_ratio": 0.917003, "quick_ratio": 0.276273, "interest_coverage": 6.961527, "pe_ratio": null, "peg_ratio": null, "price_to_sales": null, "price_to_book": null, "ev_to_ebitda": null, "enterprise_value": null, "book_value_per_share": 40.761175, "dividend_yield": null, "payout_ratio": null, "dividend_growth": null, "altman_z": 1.379709, "piotroski_f": 6}, "technical": null, "statements": {"income": [{"id": 420, "security_id": 136, "period": "annual", "fiscal_date": "2026-03-31", "reported_currency": "PKR", "revenue": 340514000000.0, "cost_of_revenue": 313508000000.0, "gross_profit": 27007000000.0, "operating_expenses": null, "operating_income": 24247000000.0, "ebitda": 31981000000.0, "ebit": null, "interest_expense": -3483000000.0, "income_before_tax": 21028000000.0, "income_tax_expense": 5757000000.0, "net_income": 15283000000.0, "eps": 2.75, "eps_diluted": null, "weighted_shares": 5548000000.0}, {"id": 421, "security_id": 136, "period": "annual", "fiscal_date": "2025-03-31", "reported_currency": "PKR", "revenue": 304375000000.0, "cost_of_revenue": 296229000000.0, "gross_profit": 8145000000.0, "operating_expenses": null, "operating_income": 5357000000.0, "ebitda": 12957000000.0, "ebit": null, "interest_expense": -5976000000.0, "income_before_tax": 286890000.0, "income_tax_expense": 1004000000.0, "net_income": -686670000.0, "eps": -0.12, "eps_diluted": null, "weighted_shares": 5508000000.0}, {"id": 422, "security_id": 136, "period": "annual", "fiscal_date": "2024-03-31", "reported_currency": "PKR", "revenue": 196485000000.0, "cost_of_revenue": 188713000000.0, "gross_profit": 7772000000.0, "operating_expenses": null, "operating_income": -1989000000.0, "ebitda": 5345000000.0, "ebit": null, "interest_expense": -8957000000.0, "income_before_tax": -3283000000.0, "income_tax_expense": 182150000.0, "net_income": -3441000000.0, "eps": -0.63, "eps_diluted": null, "weighted_shares": 5440000000.0}, {"id": 423, "security_id": 136, "period": "annual", "fiscal_date": "2023-03-31", "reported_currency": "PKR", "revenue": 199919000000.0, "cost_of_revenue": 204372000000.0, "gross_profit": -4452000000.0, "operating_expenses": null, "operating_income": -1436000000.0, "ebitda": 2133000000.0, "ebit": null, "interest_expense": -5125000000.0, "income_before_tax": -5705000000.0, "income_tax_expense": 625830000.0, "net_income": -6322000000.0, "eps": -1.19, "eps_diluted": null, "weighted_shares": 5318000000.0}, {"id": 424, "security_id": 136, "period": "annual", "fiscal_date": "2022-03-31", "reported_currency": "PKR", "revenue": 162667000000.0, "cost_of_revenue": 155920000000.0, "gross_profit": 6746000000.0, "operating_expenses": null, "operating_income": 3914000000.0, "ebitda": 8318000000.0, "ebit": null, "interest_expense": -2750000000.0, "income_before_tax": 2107000000.0, "income_tax_expense": 771070000.0, "net_income": 1336000000.0, "eps": 0.25, "eps_diluted": null, "weighted_shares": 5629000000.0}], "balance": [{"id": 419, "security_id": 136, "period": "annual", "fiscal_date": "2026-03-31", "reported_currency": "PKR", "cash_and_equivalents": 2669000000.0, "short_term_investments": null, "receivables": 41700000000.0, "inventory": 104419000000.0, "current_assets": 149443000000.0, "property_plant_equipment": null, "goodwill_intangibles": null, "total_assets": 472376000000.0, "accounts_payable": 150316000000.0, "short_term_debt": 1600000000.0, "current_liabilities": 162969000000.0, "long_term_debt": 10770000000.0, "total_debt": 17963000000.0, "total_liabilities": 246233000000.0, "retained_earnings": -9184000000.0, "total_equity": 226143000000.0}, {"id": 420, "security_id": 136, "period": "annual", "fiscal_date": "2025-03-31", "reported_currency": "PKR", "cash_and_equivalents": 2085000000.0, "short_term_investments": null, "receivables": 23600000000.0, "inventory": 44971000000.0, "current_assets": 71246000000.0, "property_plant_equipment": null, "goodwill_intangibles": null, "total_assets": 397981000000.0, "accounts_payable": 85689000000.0, "short_term_debt": 9734000000.0, "current_liabilities": 100244000000.0, "long_term_debt": 13535000000.0, "total_debt": 26963000000.0, "total_liabilities": 187202000000.0, "retained_earnings": -27277000000.0, "total_equity": 210780000000.0}, {"id": 421, "security_id": 136, "period": "annual", "fiscal_date": "2024-03-31", "reported_currency": "PKR", "cash_and_equivalents": 2198000000.0, "short_term_investments": null, "receivables": 8173000000.0, "inventory": 54711000000.0, "current_assets": 65658000000.0, "property_plant_equipment": null, "goodwill_intangibles": null, "total_assets": 395513000000.0, "accounts_payable": 74071000000.0, "short_term_debt": 23875000000.0, "current_liabilities": 103229000000.0, "long_term_debt": 21335000000.0, "total_debt": 48327000000.0, "total_liabilities": 209785000000.0, "retained_earnings": -29387000000.0, "total_equity": 185728000000.0}, {"id": 422, "security_id": 136, "period": "annual", "fiscal_date": "2023-03-31", "reported_currency": "PKR", "cash_and_equivalents": 665520000.0, "short_term_investments": null, "receivables": 10724000000.0, "inventory": 31837000000.0, "current_assets": 43370000000.0, "property_plant_equipment": null, "goodwill_intangibles": null, "total_assets": 131315000000.0, "accounts_payable": 52154000000.0, "short_term_debt": 31566000000.0, "current_liabilities": 89625000000.0, "long_term_debt": 14522000000.0, "total_debt": 49807000000.0, "total_liabilities": 116500000000.0, "retained_earnings": -29388000000.0, "total_equity": 14815000000.0}, {"id": 423, "security_id": 136, "period": "annual", "fiscal_date": "2022-03-31", "reported_currency": "PKR", "cash_and_equivalents": 1601000000.0, "short_term_investments": null, "receivables": 12284000000.0, "inventory": 26826000000.0, "current_assets": 41883000000.0, "property_plant_equipment": null, "goodwill_intangibles": null, "total_assets": 126290000000.0, "accounts_payable": 49033000000.0, "short_term_debt": 16023000000.0, "current_liabilities": 73951000000.0, "long_term_debt": 19335000000.0, "total_debt": 36542000000.0, "total_liabilities": 104542000000.0, "retained_earnings": -23427000000.0, "total_equity": 21747000000.0}], "cashflow": [{"id": 420, "security_id": 136, "period": "annual", "fiscal_date": "2026-03-31", "reported_currency": "PKR", "operating_cash_flow": 13873000000.0, "capital_expenditure": -4139000000.0, "free_cash_flow": 9734000000.0, "investing_cash_flow": -3825000000.0, "financing_cash_flow": -9464000000.0, "dividends_paid": null, "stock_repurchase": null, "net_change_in_cash": 584440000.0}, {"id": 421, "security_id": 136, "period": "annual", "fiscal_date": "2025-03-31", "reported_currency": "PKR", "operating_cash_flow": 10737000000.0, "capital_expenditure": -3052000000.0, "free_cash_flow": 7686000000.0, "investing_cash_flow": -2998000000.0, "financing_cash_flow": -7852000000.0, "dividends_paid": -20000.0, "stock_repurchase": null, "net_change_in_cash": -112850000.0}, {"id": 422, "security_id": 136, "period": "annual", "fiscal_date": "2024-03-31", "reported_currency": "PKR", "operating_cash_flow": 4705000000.0, "capital_expenditure": -1825000000.0, "free_cash_flow": 2880000000.0, "investing_cash_flow": -1781000000.0, "financing_cash_flow": -1392000000.0, "dividends_paid": null, "stock_repurchase": null, "net_change_in_cash": 1532000000.0}, {"id": 423, "security_id": 136, "period": "annual", "fiscal_date": "2023-03-31", "reported_currency": "PKR", "operating_cash_flow": -11818000000.0, "capital_expenditure": -1620000000.0, "free_cash_flow": -13438000000.0, "investing_cash_flow": -1702000000.0, "financing_cash_flow": 12584000000.0, "dividends_paid": null, "stock_repurchase": null, "net_change_in_cash": -936270000.0}, {"id": 424, "security_id": 136, "period": "annual", "fiscal_date": "2022-03-31", "reported_currency": "PKR", "operating_cash_flow": 567350000.0, "capital_expenditure": -4751000000.0, "free_cash_flow": -4184000000.0, "investing_cash_flow": -4930000000.0, "financing_cash_flow": 4042000000.0, "dividends_paid": null, "stock_repurchase": null, "net_change_in_cash": -320670000.0}]}, "patterns": [], "score_history": [{"as_of": "2026-07-24", "composite": 48.09, "fundamental": 47.99, "technical": null, "momentum": null, "quality": 40.07, "risk": 56.48}], "dividends": [], "estimates": [], "peers": [], "news": [], "insider": [], "insider_summary": null, "ai_summary": "CNERGY scores 48/100 overall \u2014 a average composite profile. Key metrics: ROE 7.0%, net margin 4.5%, debt/equity 0.08, revenue growth 11.9%. Current signal: Hold (confidence 40%). This summary is generated from computed metrics only; it is not investment advice."}