{"security": {"id": 159, "market_id": 4, "symbol": "DOL", "provider_symbol": "DOL.KA", "name": null, "asset_class": "equity", "sector": null, "industry": null, "currency": "PKR", "country": "PK", "isin": null, "figi": null, "cik": null, "market_cap": null, "shares_outstanding": null, "is_active": true, "market_code": "PSX", "region": "psx"}, "tradingview_symbol": null, "quote": null, "scores": {"id": 118, "security_id": 159, "as_of": "2026-07-24", "fundamental": 51.78, "technical": null, "momentum": null, "quality": 54.1, "risk": 85.76, "composite": 58.38, "breakdown": {"fundamental": {"score": 51.78, "coverage": 1.0, "weight_present": 1.0, "metrics": {"roe": {"label": "Return on equity", "value": 0.14344, "sub_score": 57.38, "weight": 0.14, "contribution": 8.0332}, "net_margin": {"label": "Net margin", "value": 0.088361, "sub_score": 44.18, "weight": 0.1, "contribution": 4.418}, "roa": {"label": "Return on assets", "value": 0.096073, "sub_score": 80.06, "weight": 0.08, "contribution": 6.4048}, "gross_margin": {"label": "Gross margin", "value": 0.192526, "sub_score": 32.09, "weight": 0.06, "contribution": 1.9254}, "revenue_growth": {"label": "Revenue growth", "value": -0.156843, "sub_score": 0.0, "weight": 0.1, "contribution": 0.0}, "eps_growth": {"label": "EPS growth", "value": -0.461053, "sub_score": 0.0, "weight": 0.1, "contribution": 0.0}, "debt_to_equity": {"label": "Debt / equity", "value": 0.330742, "sub_score": 86.77, "weight": 0.1, "contribution": 8.677}, "current_ratio": {"label": "Current ratio", "value": 1.480505, "sub_score": 98.05, "weight": 0.06, "contribution": 5.883}, "interest_coverage": {"label": "Interest coverage", "value": 11.409179, "sub_score": 100.0, "weight": 0.06, "contribution": 6.0}, "fcf_margin": {"label": "Free-cash-flow margin", "value": 0.029443, "sub_score": 19.63, "weight": 0.05, "contribution": 0.9815}, "piotroski_f": {"label": "Piotroski F-Score", "value": 4.0, "sub_score": 44.44, "weight": 0.08, "contribution": 3.5552}, "altman_z": {"label": "Altman Z-Score", "value": 2.812066, "sub_score": 84.34, "weight": 0.07, "contribution": 5.9038}}, "missing": [], "piotroski_criteria": {"positive_roa": true, "positive_ocf": true, "roa_improved": false, "accruals": false, "lower_leverage": true, "higher_current_ratio": false, "no_dilution": true, "higher_margin": false, "higher_turnover": false}}, "composite": {"composite": 58.38, "coverage": 0.55, "weights": {"fundamental": 0.35, "technical": 0.35, "momentum": 0.1, "quality": 0.1, "risk": 0.1}, "components": {"fundamental": {"score": 51.78, "weight": 0.35, "contribution": 32.95}, "quality": {"score": 54.1, "weight": 0.1, "contribution": 9.84}, "risk": {"score": 85.76, "weight": 0.1, "contribution": 15.59}}, "dimensions": {"momentum": {"reason": "no_technical_indicators"}, "quality": {"metrics": {"roe": {"label": "Return on equity", "value": 0.14344, "sub_score": 57.38, "weight": 0.25, "contribution": 14.345}, "net_margin": {"label": "Net margin", "value": 0.088361, "sub_score": 44.18, "weight": 0.2, "contribution": 8.836}, "gross_margin": {"label": "Gross margin", "value": 0.192526, "sub_score": 32.09, "weight": 0.15, "contribution": 4.8135}, "piotroski_f": {"label": "Piotroski F-Score", "value": 4.0, "sub_score": 44.44, "weight": 0.25, "contribution": 11.11}, "interest_coverage": {"label": "Interest coverage", "value": 11.409179, "sub_score": 100.0, "weight": 0.15, "contribution": 15.0}}, "missing": [], "coverage": 1.0}, "risk": {"metrics": {"debt_to_equity": {"label": "Debt / equity", "value": 0.330742, "sub_score": 86.77, "weight": 0.35, "contribution": 30.3695}, "altman_z": {"label": "Altman Z-Score", "value": 2.812066, "sub_score": 84.34, "weight": 0.25, "contribution": 21.085}}, "missing": ["volatility"], "coverage": 0.6}}}}}, "signal": {"id": 121, "security_id": 159, "as_of": "2026-07-24", "signal_type": "hold", "confidence": 0.476, "rationale": "Composite 58/100 \u2192 Hold. Top drivers: risk 86, quality 54, fundamental 52.", "triggers": {"fundamental": 51.78, "quality": 54.1, "risk": 85.76}, "label": "Hold"}, "fundamentals": {"security_id": 159, "as_of": "2026-03-31", "pe_ttm": null, "roe": 0.14344, "debt_to_equity": 0.330742, "revenue_growth": -0.156843, "eps_growth": -0.461053, "net_margin": 0.088361, "dividend_yield": null, "market_cap": null}, "ratios": {"id": 118, "security_id": 159, "period": "annual", "fiscal_date": "2026-03-31", "gross_margin": 0.192526, "operating_margin": 0.081491, "net_margin": 0.088361, "roe": 0.14344, "roa": 0.096073, "roic": 0.092946, "revenue_growth": -0.156843, "revenue_cagr_3y": -0.08107, "eps_growth": -0.461053, "eps_cagr_3y": -0.32943, "debt_to_equity": 0.330742, "current_ratio": 1.480505, "quick_ratio": 0.731078, "interest_coverage": 11.409179, "pe_ratio": null, "peg_ratio": null, "price_to_sales": null, "price_to_book": null, "ev_to_ebitda": null, "enterprise_value": null, "book_value_per_share": 17.097143, "dividend_yield": null, "payout_ratio": 1.564654, "dividend_growth": 0.013609, "altman_z": 2.812066, "piotroski_f": 4}, "technical": null, "statements": {"income": [{"id": 535, "security_id": 159, "period": "annual", "fiscal_date": "2026-03-31", "reported_currency": "PKR", "revenue": 5064000000.0, "cost_of_revenue": 4090000000.0, "gross_profit": 974950000.0, "operating_expenses": null, "operating_income": 412670000.0, "ebitda": 740780000.0, "ebit": null, "interest_expense": -36170000.0, "income_before_tax": 529860000.0, "income_tax_expense": 82400000.0, "net_income": 447460000.0, "eps": 2.56, "eps_diluted": null, "weighted_shares": 175000000.0}, {"id": 536, "security_id": 159, "period": "annual", "fiscal_date": "2025-03-31", "reported_currency": "PKR", "revenue": 6006000000.0, "cost_of_revenue": 4197000000.0, "gross_profit": 1809000000.0, "operating_expenses": null, "operating_income": 1113000000.0, "ebitda": 1502000000.0, "ebit": null, "interest_expense": -4000000.0, "income_before_tax": 1341000000.0, "income_tax_expense": 508680000.0, "net_income": 832060000.0, "eps": 4.75, "eps_diluted": null, "weighted_shares": 175000000.0}, {"id": 537, "security_id": 159, "period": "annual", "fiscal_date": "2024-03-31", "reported_currency": "PKR", "revenue": 5902000000.0, "cost_of_revenue": 4532000000.0, "gross_profit": 1370000000.0, "operating_expenses": null, "operating_income": 1019000000.0, "ebitda": 1411000000.0, "ebit": null, "interest_expense": -12590000.0, "income_before_tax": 1025000000.0, "income_tax_expense": 519250000.0, "net_income": 505520000.0, "eps": 2.89, "eps_diluted": null, "weighted_shares": 175000000.0}, {"id": 538, "security_id": 159, "period": "annual", "fiscal_date": "2023-03-31", "reported_currency": "PKR", "revenue": 6526000000.0, "cost_of_revenue": 3824000000.0, "gross_profit": 2702000000.0, "operating_expenses": null, "operating_income": 2277000000.0, "ebitda": 2646000000.0, "ebit": null, "interest_expense": -31950000.0, "income_before_tax": 2282000000.0, "income_tax_expense": 796430000.0, "net_income": 1486000000.0, "eps": 8.49, "eps_diluted": null, "weighted_shares": 175000000.0}, {"id": 539, "security_id": 159, "period": "annual", "fiscal_date": "2022-03-31", "reported_currency": "PKR", "revenue": 3593000000.0, "cost_of_revenue": 2848000000.0, "gross_profit": 745070000.0, "operating_expenses": null, "operating_income": 530820000.0, "ebitda": 855390000.0, "ebit": null, "interest_expense": -56870000.0, "income_before_tax": 451630000.0, "income_tax_expense": 122430000.0, "net_income": 329190000.0, "eps": 1.88, "eps_diluted": null, "weighted_shares": 175000000.0}], "balance": [{"id": 533, "security_id": 159, "period": "annual", "fiscal_date": "2026-03-31", "reported_currency": "PKR", "cash_and_equivalents": 232130000.0, "short_term_investments": 563360000.0, "receivables": 479540000.0, "inventory": 1307000000.0, "current_assets": 2582000000.0, "property_plant_equipment": null, "goodwill_intangibles": null, "total_assets": 4900000000.0, "accounts_payable": 755040000.0, "short_term_debt": 918740000.0, "current_liabilities": 1744000000.0, "long_term_debt": 48550000.0, "total_debt": 989580000.0, "total_liabilities": 1908000000.0, "retained_earnings": 1241000000.0, "total_equity": 2992000000.0}, {"id": 534, "security_id": 159, "period": "annual", "fiscal_date": "2025-03-31", "reported_currency": "PKR", "cash_and_equivalents": 336260000.0, "short_term_investments": 451060000.0, "receivables": 223580000.0, "inventory": 1148000000.0, "current_assets": 2280000000.0, "property_plant_equipment": null, "goodwill_intangibles": null, "total_assets": 4415000000.0, "accounts_payable": 223490000.0, "short_term_debt": null, "current_liabilities": 859220000.0, "long_term_debt": 70840000.0, "total_debt": 97740000.0, "total_liabilities": 1169000000.0, "retained_earnings": 1493000000.0, "total_equity": 3247000000.0}, {"id": 535, "security_id": 159, "period": "annual", "fiscal_date": "2024-03-31", "reported_currency": "PKR", "cash_and_equivalents": 253150000.0, "short_term_investments": 132270000.0, "receivables": 220370000.0, "inventory": 1417000000.0, "current_assets": 2167000000.0, "property_plant_equipment": null, "goodwill_intangibles": null, "total_assets": 4392000000.0, "accounts_payable": 351180000.0, "short_term_debt": null, "current_liabilities": 978180000.0, "long_term_debt": 98650000.0, "total_debt": 129490000.0, "total_liabilities": 1275000000.0, "retained_earnings": 1363000000.0, "total_equity": 3116000000.0}, {"id": 536, "security_id": 159, "period": "annual", "fiscal_date": "2023-03-31", "reported_currency": "PKR", "cash_and_equivalents": 92580000.0, "short_term_investments": 542950000.0, "receivables": 256390000.0, "inventory": 959650000.0, "current_assets": 1918000000.0, "property_plant_equipment": null, "goodwill_intangibles": null, "total_assets": 4416000000.0, "accounts_payable": 160120000.0, "short_term_debt": 6000000.0, "current_liabilities": 1092000000.0, "long_term_debt": 104930000.0, "total_debt": 156420000.0, "total_liabilities": 1456000000.0, "retained_earnings": 1206000000.0, "total_equity": 2960000000.0}, {"id": 537, "security_id": 159, "period": "annual", "fiscal_date": "2022-03-31", "reported_currency": "PKR", "cash_and_equivalents": 62340000.0, "short_term_investments": null, "receivables": 259450000.0, "inventory": 572410000.0, "current_assets": 1093000000.0, "property_plant_equipment": null, "goodwill_intangibles": null, "total_assets": 3629000000.0, "accounts_payable": 354720000.0, "short_term_debt": 13950000.0, "current_liabilities": 840700000.0, "long_term_debt": 377140000.0, "total_debt": 475770000.0, "total_liabilities": 1454000000.0, "retained_earnings": 420990000.0, "total_equity": 2174000000.0}], "cashflow": [{"id": 535, "security_id": 159, "period": "annual", "fiscal_date": "2026-03-31", "reported_currency": "PKR", "operating_cash_flow": 259660000.0, "capital_expenditure": -110560000.0, "free_cash_flow": 149100000.0, "investing_cash_flow": -539560000.0, "financing_cash_flow": 191720000.0, "dividends_paid": -700120000.0, "stock_repurchase": null, "net_change_in_cash": -88180000.0}, {"id": 536, "security_id": 159, "period": "annual", "fiscal_date": "2025-03-31", "reported_currency": "PKR", "operating_cash_flow": 1355000000.0, "capital_expenditure": -324690000.0, "free_cash_flow": 1030000000.0, "investing_cash_flow": -546690000.0, "financing_cash_flow": -835360000.0, "dividends_paid": -690720000.0, "stock_repurchase": null, "net_change_in_cash": -27270000.0}, {"id": 537, "security_id": 159, "period": "annual", "fiscal_date": "2024-03-31", "reported_currency": "PKR", "operating_cash_flow": 267570000.0, "capital_expenditure": -207580000.0, "free_cash_flow": 59990000.0, "investing_cash_flow": 298000000.0, "financing_cash_flow": -303240000.0, "dividends_paid": -347610000.0, "stock_repurchase": null, "net_change_in_cash": 262340000.0}, {"id": 538, "security_id": 159, "period": "annual", "fiscal_date": "2023-03-31", "reported_currency": "PKR", "operating_cash_flow": 1944000000.0, "capital_expenditure": -262110000.0, "free_cash_flow": 1682000000.0, "investing_cash_flow": -848920000.0, "financing_cash_flow": -1057000000.0, "dividends_paid": -693960000.0, "stock_repurchase": null, "net_change_in_cash": 38190000.0}, {"id": 539, "security_id": 159, "period": "annual", "fiscal_date": "2022-03-31", "reported_currency": "PKR", "operating_cash_flow": 568280000.0, "capital_expenditure": -322660000.0, "free_cash_flow": 245620000.0, "investing_cash_flow": 241550000.0, "financing_cash_flow": -856380000.0, "dividends_paid": -173760000.0, "stock_repurchase": null, "net_change_in_cash": -46550000.0}]}, "patterns": [], "score_history": [{"as_of": "2026-07-24", "composite": 58.38, "fundamental": 51.78, "technical": null, "momentum": null, "quality": 54.1, "risk": 85.76}], "dividends": [], "estimates": [], "peers": [], "news": [], "insider": [], "insider_summary": null, "ai_summary": "DOL scores 58/100 overall \u2014 a average composite profile. Key metrics: ROE 14.3%, net margin 8.8%, debt/equity 0.33, revenue growth -15.7%. Current signal: Hold (confidence 48%). This summary is generated from computed metrics only; it is not investment advice."}