{"security": {"id": 332, "market_id": 4, "symbol": "NESTLE", "provider_symbol": "NESTLE.KA", "name": null, "asset_class": "equity", "sector": null, "industry": null, "currency": "PKR", "country": "PK", "isin": null, "figi": null, "cik": null, "market_cap": null, "shares_outstanding": null, "is_active": true, "market_code": "PSX", "region": "psx"}, "tradingview_symbol": null, "quote": null, "scores": {"id": 291, "security_id": 332, "as_of": "2026-07-24", "fundamental": 78.81, "technical": null, "momentum": null, "quality": 77.38, "risk": 98.5, "composite": 82.13, "breakdown": {"fundamental": {"score": 78.81, "coverage": 1.0, "weight_present": 1.0, "metrics": {"roe": {"label": "Return on equity", "value": 0.70774, "sub_score": 100.0, "weight": 0.14, "contribution": 14.0}, "net_margin": {"label": "Net margin", "value": 0.08809, "sub_score": 44.05, "weight": 0.1, "contribution": 4.405}, "roa": {"label": "Return on assets", "value": 0.183715, "sub_score": 100.0, "weight": 0.08, "contribution": 8.0}, "gross_margin": {"label": "Gross margin", "value": 0.364779, "sub_score": 60.8, "weight": 0.06, "contribution": 3.648}, "revenue_growth": {"label": "Revenue growth", "value": 0.071479, "sub_score": 48.99, "weight": 0.1, "contribution": 4.899}, "eps_growth": {"label": "EPS growth", "value": 0.211501, "sub_score": 77.88, "weight": 0.1, "contribution": 7.788}, "debt_to_equity": {"label": "Debt / equity", "value": 0.064286, "sub_score": 97.43, "weight": 0.1, "contribution": 9.743}, "current_ratio": {"label": "Current ratio", "value": 0.951096, "sub_score": 45.11, "weight": 0.06, "contribution": 2.7066}, "interest_coverage": {"label": "Interest coverage", "value": 81.018759, "sub_score": 100.0, "weight": 0.06, "contribution": 6.0}, "fcf_margin": {"label": "Free-cash-flow margin", "value": 0.131887, "sub_score": 87.92, "weight": 0.05, "contribution": 4.396}, "piotroski_f": {"label": "Piotroski F-Score", "value": 7.0, "sub_score": 77.78, "weight": 0.08, "contribution": 6.2224}, "altman_z": {"label": "Altman Z-Score", "value": 3.509981, "sub_score": 100.0, "weight": 0.07, "contribution": 7.0}}, "missing": [], "piotroski_criteria": {"positive_roa": true, "positive_ocf": true, "roa_improved": true, "accruals": true, "lower_leverage": false, "higher_current_ratio": true, "no_dilution": true, "higher_margin": true, "higher_turnover": false}}, "composite": {"composite": 82.13, "coverage": 0.55, "weights": {"fundamental": 0.35, "technical": 0.35, "momentum": 0.1, "quality": 0.1, "risk": 0.1}, "components": {"fundamental": {"score": 78.81, "weight": 0.35, "contribution": 50.15}, "quality": {"score": 77.38, "weight": 0.1, "contribution": 14.07}, "risk": {"score": 98.5, "weight": 0.1, "contribution": 17.91}}, "dimensions": {"momentum": {"reason": "no_technical_indicators"}, "quality": {"metrics": {"roe": {"label": "Return on equity", "value": 0.70774, "sub_score": 100.0, "weight": 0.25, "contribution": 25.0}, "net_margin": {"label": "Net margin", "value": 0.08809, "sub_score": 44.05, "weight": 0.2, "contribution": 8.81}, "gross_margin": {"label": "Gross margin", "value": 0.364779, "sub_score": 60.8, "weight": 0.15, "contribution": 9.12}, "piotroski_f": {"label": "Piotroski F-Score", "value": 7.0, "sub_score": 77.78, "weight": 0.25, "contribution": 19.445}, "interest_coverage": {"label": "Interest coverage", "value": 81.018759, "sub_score": 100.0, "weight": 0.15, "contribution": 15.0}}, "missing": [], "coverage": 1.0}, "risk": {"metrics": {"debt_to_equity": {"label": "Debt / equity", "value": 0.064286, "sub_score": 97.43, "weight": 0.35, "contribution": 34.1005}, "altman_z": {"label": "Altman Z-Score", "value": 3.509981, "sub_score": 100.0, "weight": 0.25, "contribution": 25.0}}, "missing": ["volatility"], "coverage": 0.6}}}}}, "signal": {"id": 294, "security_id": 332, "as_of": "2026-07-24", "signal_type": "strong_buy", "confidence": 0.377, "rationale": "Composite 82/100 \u2192 Strong Buy. Top drivers: risk 98, fundamental 79, quality 77.", "triggers": {"fundamental": 78.81, "quality": 77.38, "risk": 98.5}, "label": "Strong Buy"}, "fundamentals": {"security_id": 332, "as_of": "2026-03-31", "pe_ttm": null, "roe": 0.70774, "debt_to_equity": 0.064286, "revenue_growth": 0.071479, "eps_growth": 0.211501, "net_margin": 0.08809, "dividend_yield": null, "market_cap": null}, "ratios": {"id": 291, "security_id": 332, "period": "annual", "fiscal_date": "2026-03-31", "gross_margin": 0.364779, "operating_margin": 0.161712, "net_margin": 0.08809, "roe": 0.70774, "roa": 0.183715, "roic": 0.817929, "revenue_growth": 0.071479, "revenue_cagr_3y": 0.051572, "eps_growth": 0.211501, "eps_cagr_3y": 0.031728, "debt_to_equity": 0.064286, "current_ratio": 0.951096, "quick_ratio": 0.421305, "interest_coverage": 81.018759, "pe_ratio": null, "peg_ratio": null, "price_to_sales": null, "price_to_book": null, "ev_to_ebitda": null, "enterprise_value": null, "book_value_per_share": 597.333333, "dividend_yield": null, "payout_ratio": 0.839783, "dividend_growth": 0.031078, "altman_z": 3.509981, "piotroski_f": 7}, "technical": null, "statements": {"income": [{"id": 1406, "security_id": 332, "period": "annual", "fiscal_date": "2026-03-31", "reported_currency": "PKR", "revenue": 202712000000.0, "cost_of_revenue": 128767000000.0, "gross_profit": 73945000000.0, "operating_expenses": null, "operating_income": 32781000000.0, "ebitda": 36987000000.0, "ebit": null, "interest_expense": -404610000.0, "income_before_tax": 30684000000.0, "income_tax_expense": 12827000000.0, "net_income": 17857000000.0, "eps": 393.75, "eps_diluted": null, "weighted_shares": 45000000.0}, {"id": 1407, "security_id": 332, "period": "annual", "fiscal_date": "2025-03-31", "reported_currency": "PKR", "revenue": 189189000000.0, "cost_of_revenue": 120215000000.0, "gross_profit": 68973000000.0, "operating_expenses": null, "operating_income": 29140000000.0, "ebitda": 32928000000.0, "ebit": null, "interest_expense": -1901000000.0, "income_before_tax": 25546000000.0, "income_tax_expense": 10807000000.0, "net_income": 14739000000.0, "eps": 325.01, "eps_diluted": null, "weighted_shares": 45000000.0}, {"id": 1408, "security_id": 332, "period": "annual", "fiscal_date": "2024-03-31", "reported_currency": "PKR", "revenue": 205408000000.0, "cost_of_revenue": 133223000000.0, "gross_profit": 72185000000.0, "operating_expenses": null, "operating_income": 33410000000.0, "ebitda": 37090000000.0, "ebit": null, "interest_expense": -2581000000.0, "income_before_tax": 29225000000.0, "income_tax_expense": 13326000000.0, "net_income": 15899000000.0, "eps": 350.58, "eps_diluted": null, "weighted_shares": 45000000.0}, {"id": 1409, "security_id": 332, "period": "annual", "fiscal_date": "2023-03-31", "reported_currency": "PKR", "revenue": 174326000000.0, "cost_of_revenue": 113222000000.0, "gross_profit": 61104000000.0, "operating_expenses": null, "operating_income": 30152000000.0, "ebitda": 33868000000.0, "ebit": null, "interest_expense": -2331000000.0, "income_before_tax": 24785000000.0, "income_tax_expense": 8526000000.0, "net_income": 16259000000.0, "eps": 358.53, "eps_diluted": null, "weighted_shares": 45000000.0}, {"id": 1410, "security_id": 332, "period": "annual", "fiscal_date": "2022-03-31", "reported_currency": "PKR", "revenue": 138743000000.0, "cost_of_revenue": 95563000000.0, "gross_profit": 43180000000.0, "operating_expenses": null, "operating_income": 23940000000.0, "ebitda": 27564000000.0, "ebit": null, "interest_expense": -1947000000.0, "income_before_tax": 19712000000.0, "income_tax_expense": 5701000000.0, "net_income": 14011000000.0, "eps": 308.96, "eps_diluted": null, "weighted_shares": 45000000.0}], "balance": [{"id": 1394, "security_id": 332, "period": "annual", "fiscal_date": "2026-03-31", "reported_currency": "PKR", "cash_and_equivalents": 5284000000.0, "short_term_investments": 7260000000.0, "receivables": 9690000000.0, "inventory": 36963000000.0, "current_assets": 66357000000.0, "property_plant_equipment": null, "goodwill_intangibles": null, "total_assets": 104043000000.0, "accounts_payable": 64505000000.0, "short_term_debt": null, "current_liabilities": 69769000000.0, "long_term_debt": null, "total_debt": 1728000000.0, "total_liabilities": 77163000000.0, "retained_earnings": 26177000000.0, "total_equity": 26880000000.0}, {"id": 1395, "security_id": 332, "period": "annual", "fiscal_date": "2025-03-31", "reported_currency": "PKR", "cash_and_equivalents": 3941000000.0, "short_term_investments": null, "receivables": 9304000000.0, "inventory": 36415000000.0, "current_assets": 53762000000.0, "property_plant_equipment": null, "goodwill_intangibles": null, "total_assets": 90356000000.0, "accounts_payable": 53008000000.0, "short_term_debt": 2007000000.0, "current_liabilities": 60088000000.0, "long_term_debt": null, "total_debt": 4987000000.0, "total_liabilities": 66774000000.0, "retained_earnings": 22879000000.0, "total_equity": 23582000000.0}, {"id": 1396, "security_id": 332, "period": "annual", "fiscal_date": "2024-03-31", "reported_currency": "PKR", "cash_and_equivalents": 1375000000.0, "short_term_investments": null, "receivables": 21861000000.0, "inventory": 42092000000.0, "current_assets": 70411000000.0, "property_plant_equipment": null, "goodwill_intangibles": null, "total_assets": 104592000000.0, "accounts_payable": 58667000000.0, "short_term_debt": 6047000000.0, "current_liabilities": 76279000000.0, "long_term_debt": 7905000000.0, "total_debt": 15664000000.0, "total_liabilities": 88936000000.0, "retained_earnings": 14953000000.0, "total_equity": 15656000000.0}, {"id": 1397, "security_id": 332, "period": "annual", "fiscal_date": "2023-03-31", "reported_currency": "PKR", "cash_and_equivalents": 1350000000.0, "short_term_investments": null, "receivables": 15293000000.0, "inventory": 38927000000.0, "current_assets": 62117000000.0, "property_plant_equipment": null, "goodwill_intangibles": null, "total_assets": 94695000000.0, "accounts_payable": 44764000000.0, "short_term_debt": 5491000000.0, "current_liabilities": 70520000000.0, "long_term_debt": 7946000000.0, "total_debt": 23883000000.0, "total_liabilities": 83265000000.0, "retained_earnings": 10727000000.0, "total_equity": 11430000000.0}, {"id": 1398, "security_id": 332, "period": "annual", "fiscal_date": "2022-03-31", "reported_currency": "PKR", "cash_and_equivalents": 1139000000.0, "short_term_investments": null, "receivables": 9550000000.0, "inventory": 27546000000.0, "current_assets": 42024000000.0, "property_plant_equipment": null, "goodwill_intangibles": null, "total_assets": 72849000000.0, "accounts_payable": 30225000000.0, "short_term_debt": 13226000000.0, "current_liabilities": 47798000000.0, "long_term_debt": 10952000000.0, "total_debt": 24322000000.0, "total_liabilities": 62986000000.0, "retained_earnings": 9155000000.0, "total_equity": 9863000000.0}], "cashflow": [{"id": 1399, "security_id": 332, "period": "annual", "fiscal_date": "2026-03-31", "reported_currency": "PKR", "operating_cash_flow": 31099000000.0, "capital_expenditure": -4365000000.0, "free_cash_flow": 26735000000.0, "investing_cash_flow": -11052000000.0, "financing_cash_flow": -18698000000.0, "dividends_paid": -14996000000.0, "stock_repurchase": null, "net_change_in_cash": 1350000000.0}, {"id": 1400, "security_id": 332, "period": "annual", "fiscal_date": "2025-03-31", "reported_currency": "PKR", "operating_cash_flow": 32404000000.0, "capital_expenditure": -4740000000.0, "free_cash_flow": 27665000000.0, "investing_cash_flow": -4632000000.0, "financing_cash_flow": -22055000000.0, "dividends_paid": -14544000000.0, "stock_repurchase": null, "net_change_in_cash": 5717000000.0}, {"id": 1401, "security_id": 332, "period": "annual", "fiscal_date": "2024-03-31", "reported_currency": "PKR", "operating_cash_flow": 23217000000.0, "capital_expenditure": -3714000000.0, "free_cash_flow": 19503000000.0, "investing_cash_flow": -3673000000.0, "financing_cash_flow": -17706000000.0, "dividends_paid": -10714000000.0, "stock_repurchase": null, "net_change_in_cash": 1838000000.0}, {"id": 1402, "security_id": 332, "period": "annual", "fiscal_date": "2023-03-31", "reported_currency": "PKR", "operating_cash_flow": 14061000000.0, "capital_expenditure": -3417000000.0, "free_cash_flow": 10644000000.0, "investing_cash_flow": -3008000000.0, "financing_cash_flow": -12587000000.0, "dividends_paid": -8917000000.0, "stock_repurchase": null, "net_change_in_cash": -1534000000.0}, {"id": 1403, "security_id": 332, "period": "annual", "fiscal_date": "2022-03-31", "reported_currency": "PKR", "operating_cash_flow": 18093000000.0, "capital_expenditure": -2652000000.0, "free_cash_flow": 15441000000.0, "investing_cash_flow": -2537000000.0, "financing_cash_flow": -13513000000.0, "dividends_paid": -11610000000.0, "stock_repurchase": null, "net_change_in_cash": 2043000000.0}]}, "patterns": [], "score_history": [{"as_of": "2026-07-24", "composite": 82.13, "fundamental": 78.81, "technical": null, "momentum": null, "quality": 77.38, "risk": 98.5}], "dividends": [], "estimates": [], "peers": [], "news": [], "insider": [], "insider_summary": null, "ai_summary": "NESTLE scores 82/100 overall \u2014 a excellent composite profile. Key metrics: ROE 70.8%, net margin 8.8%, debt/equity 0.06, revenue growth 7.1%. Current signal: Strong Buy (confidence 38%). This summary is generated from computed metrics only; it is not investment advice."}