{"security": {"id": 451, "market_id": 4, "symbol": "SYM", "provider_symbol": "SYM.KA", "name": null, "asset_class": "equity", "sector": null, "industry": null, "currency": "PKR", "country": "PK", "isin": null, "figi": null, "cik": null, "market_cap": null, "shares_outstanding": null, "is_active": true, "market_code": "PSX", "region": "psx"}, "tradingview_symbol": null, "quote": null, "scores": {"id": 410, "security_id": 451, "as_of": "2026-07-24", "fundamental": 66.67, "technical": null, "momentum": null, "quality": 64.02, "risk": 89.38, "composite": 70.32, "breakdown": {"fundamental": {"score": 66.67, "coverage": 1.0, "weight_present": 1.0, "metrics": {"roe": {"label": "Return on equity", "value": 0.115019, "sub_score": 46.01, "weight": 0.14, "contribution": 6.4414}, "net_margin": {"label": "Net margin", "value": 0.226092, "sub_score": 100.0, "weight": 0.1, "contribution": 10.0}, "roa": {"label": "Return on assets", "value": 0.08553, "sub_score": 71.27, "weight": 0.08, "contribution": 5.7016}, "gross_margin": {"label": "Gross margin", "value": 0.540114, "sub_score": 90.02, "weight": 0.06, "contribution": 5.4012}, "revenue_growth": {"label": "Revenue growth", "value": 0.008144, "sub_score": 30.9, "weight": 0.1, "contribution": 3.09}, "eps_growth": {"label": "EPS growth", "value": 0.016129, "sub_score": 29.03, "weight": 0.1, "contribution": 2.903}, "debt_to_equity": {"label": "Debt / equity", "value": 0.232537, "sub_score": 90.7, "weight": 0.1, "contribution": 9.07}, "current_ratio": {"label": "Current ratio", "value": 2.317658, "sub_score": 100.0, "weight": 0.06, "contribution": 6.0}, "interest_coverage": {"label": "Interest coverage", "value": 7.408656, "sub_score": 71.21, "weight": 0.06, "contribution": 4.2726}, "fcf_margin": {"label": "Free-cash-flow margin", "value": 0.763667, "sub_score": 100.0, "weight": 0.05, "contribution": 5.0}, "piotroski_f": {"label": "Piotroski F-Score", "value": 3.0, "sub_score": 33.33, "weight": 0.08, "contribution": 2.6664}, "altman_z": {"label": "Altman Z-Score", "value": 2.850284, "sub_score": 87.52, "weight": 0.07, "contribution": 6.1264}}, "missing": [], "piotroski_criteria": {"positive_roa": true, "positive_ocf": true, "roa_improved": false, "accruals": true, "lower_leverage": false, "higher_current_ratio": false, "no_dilution": false, "higher_margin": false, "higher_turnover": false}}, "composite": {"composite": 70.32, "coverage": 0.55, "weights": {"fundamental": 0.35, "technical": 0.35, "momentum": 0.1, "quality": 0.1, "risk": 0.1}, "components": {"fundamental": {"score": 66.67, "weight": 0.35, "contribution": 42.43}, "quality": {"score": 64.02, "weight": 0.1, "contribution": 11.64}, "risk": {"score": 89.38, "weight": 0.1, "contribution": 16.25}}, "dimensions": {"momentum": {"reason": "no_technical_indicators"}, "quality": {"metrics": {"roe": {"label": "Return on equity", "value": 0.115019, "sub_score": 46.01, "weight": 0.25, "contribution": 11.5025}, "net_margin": {"label": "Net margin", "value": 0.226092, "sub_score": 100.0, "weight": 0.2, "contribution": 20.0}, "gross_margin": {"label": "Gross margin", "value": 0.540114, "sub_score": 90.02, "weight": 0.15, "contribution": 13.503}, "piotroski_f": {"label": "Piotroski F-Score", "value": 3.0, "sub_score": 33.33, "weight": 0.25, "contribution": 8.3325}, "interest_coverage": {"label": "Interest coverage", "value": 7.408656, "sub_score": 71.21, "weight": 0.15, "contribution": 10.6815}}, "missing": [], "coverage": 1.0}, "risk": {"metrics": {"debt_to_equity": {"label": "Debt / equity", "value": 0.232537, "sub_score": 90.7, "weight": 0.35, "contribution": 31.745}, "altman_z": {"label": "Altman Z-Score", "value": 2.850284, "sub_score": 87.52, "weight": 0.25, "contribution": 21.88}}, "missing": ["volatility"], "coverage": 0.6}}}}}, "signal": {"id": 413, "security_id": 451, "as_of": "2026-07-24", "signal_type": "buy", "confidence": 0.447, "rationale": "Composite 70/100 \u2192 Buy. Top drivers: risk 89, fundamental 67, quality 64.", "triggers": {"fundamental": 66.67, "quality": 64.02, "risk": 89.38}, "label": "Buy"}, "fundamentals": {"security_id": 451, "as_of": "2026-03-31", "pe_ttm": null, "roe": 0.115019, "debt_to_equity": 0.232537, "revenue_growth": 0.008144, "eps_growth": 0.016129, "net_margin": 0.226092, "dividend_yield": null, "market_cap": null}, "ratios": {"id": 410, "security_id": 451, "period": "annual", "fiscal_date": "2026-03-31", "gross_margin": 0.540114, "operating_margin": 0.261154, "net_margin": 0.226092, "roe": 0.115019, "roa": 0.08553, "roic": 0.095611, "revenue_growth": 0.008144, "revenue_cagr_3y": 0.187566, "eps_growth": 0.016129, "eps_cagr_3y": 0.027947, "debt_to_equity": 0.232537, "current_ratio": 2.317658, "quick_ratio": 2.317658, "interest_coverage": 7.408656, "pe_ratio": null, "peg_ratio": null, "price_to_sales": null, "price_to_book": null, "ev_to_ebitda": null, "enterprise_value": null, "book_value_per_share": 7.414035, "dividend_yield": null, "payout_ratio": 0.072175, "dividend_growth": -0.563983, "altman_z": 2.850284, "piotroski_f": 3}, "technical": null, "statements": {"income": [{"id": 2004, "security_id": 451, "period": "annual", "fiscal_date": "2026-03-31", "reported_currency": "PKR", "revenue": 799720000.0, "cost_of_revenue": 367790000.0, "gross_profit": 431940000.0, "operating_expenses": null, "operating_income": 208850000.0, "ebitda": 273640000.0, "ebit": null, "interest_expense": -28190000.0, "income_before_tax": 201150000.0, "income_tax_expense": 17640000.0, "net_income": 180810000.0, "eps": 0.63, "eps_diluted": null, "weighted_shares": 285000000.0}, {"id": 2005, "security_id": 451, "period": "annual", "fiscal_date": "2025-03-31", "reported_currency": "PKR", "revenue": 793260000.0, "cost_of_revenue": 322520000.0, "gross_profit": 470750000.0, "operating_expenses": null, "operating_income": 225570000.0, "ebitda": 294290000.0, "ebit": null, "interest_expense": -47720000.0, "income_before_tax": 188510000.0, "income_tax_expense": 19920000.0, "net_income": 168680000.0, "eps": 0.62, "eps_diluted": null, "weighted_shares": 271000000.0}, {"id": 2006, "security_id": 451, "period": "annual", "fiscal_date": "2024-03-31", "reported_currency": "PKR", "revenue": 475580000.0, "cost_of_revenue": 177050000.0, "gross_profit": 298540000.0, "operating_expenses": null, "operating_income": 184590000.0, "ebitda": 198490000.0, "ebit": null, "interest_expense": -17290000.0, "income_before_tax": 204920000.0, "income_tax_expense": 22350000.0, "net_income": 182420000.0, "eps": 0.69, "eps_diluted": null, "weighted_shares": 264000000.0}, {"id": 2007, "security_id": 451, "period": "annual", "fiscal_date": "2023-03-31", "reported_currency": "PKR", "revenue": 477490000.0, "cost_of_revenue": 349930000.0, "gross_profit": 127560000.0, "operating_expenses": null, "operating_income": 151100000.0, "ebitda": 153690000.0, "ebit": null, "interest_expense": -8790000.0, "income_before_tax": 147470000.0, "income_tax_expense": 32440000.0, "net_income": 115010000.0, "eps": 0.58, "eps_diluted": null, "weighted_shares": 197000000.0}, {"id": 2008, "security_id": 451, "period": "annual", "fiscal_date": "2021-06-30", "reported_currency": "PKR", "revenue": 286650000.0, "cost_of_revenue": null, "gross_profit": 286650000.0, "operating_expenses": null, "operating_income": 91860000.0, "ebitda": null, "ebit": null, "interest_expense": -9380000.0, "income_before_tax": 87840000.0, "income_tax_expense": 30360000.0, "net_income": 57480000.0, "eps": 0.68, "eps_diluted": null, "weighted_shares": 253000000.0}], "balance": [{"id": 1987, "security_id": 451, "period": "annual", "fiscal_date": "2026-03-31", "reported_currency": "PKR", "cash_and_equivalents": 611540000.0, "short_term_investments": 73000000.0, "receivables": 439620000.0, "inventory": null, "current_assets": 1238000000.0, "property_plant_equipment": null, "goodwill_intangibles": null, "total_assets": 2851000000.0, "accounts_payable": 43500000.0, "short_term_debt": 338010000.0, "current_liabilities": 534160000.0, "long_term_debt": null, "total_debt": 491350000.0, "total_liabilities": 737370000.0, "retained_earnings": 636250000.0, "total_equity": 2113000000.0}, {"id": 1988, "security_id": 451, "period": "annual", "fiscal_date": "2025-03-31", "reported_currency": "PKR", "cash_and_equivalents": 89060000.0, "short_term_investments": 73000000.0, "receivables": 556690000.0, "inventory": null, "current_assets": 771260000.0, "property_plant_equipment": null, "goodwill_intangibles": null, "total_assets": 1377000000.0, "accounts_payable": 127700000.0, "short_term_debt": 122270000.0, "current_liabilities": 271200000.0, "long_term_debt": null, "total_debt": 207600000.0, "total_liabilities": 346520000.0, "retained_earnings": 472280000.0, "total_equity": 1031000000.0}, {"id": 1989, "security_id": 451, "period": "annual", "fiscal_date": "2024-03-31", "reported_currency": "PKR", "cash_and_equivalents": 155820000.0, "short_term_investments": 73000000.0, "receivables": 603760000.0, "inventory": null, "current_assets": 835110000.0, "property_plant_equipment": null, "goodwill_intangibles": null, "total_assets": 1229000000.0, "accounts_payable": 147030000.0, "short_term_debt": 103310000.0, "current_liabilities": 259270000.0, "long_term_debt": null, "total_debt": 186540000.0, "total_liabilities": 341210000.0, "retained_earnings": 329650000.0, "total_equity": 888160000.0}, {"id": 1990, "security_id": 451, "period": "annual", "fiscal_date": "2023-03-31", "reported_currency": "PKR", "cash_and_equivalents": 7960000.0, "short_term_investments": null, "receivables": 360580000.0, "inventory": null, "current_assets": 400100000.0, "property_plant_equipment": null, "goodwill_intangibles": null, "total_assets": 455230000.0, "accounts_payable": 13370000.0, "short_term_debt": 55560000.0, "current_liabilities": 94130000.0, "long_term_debt": null, "total_debt": 57180000.0, "total_liabilities": 96820000.0, "retained_earnings": 161380000.0, "total_equity": 358410000.0}, {"id": 1991, "security_id": 451, "period": "annual", "fiscal_date": "2021-06-30", "reported_currency": "PKR", "cash_and_equivalents": 270000.0, "short_term_investments": 38330000.0, "receivables": 203890000.0, "inventory": null, "current_assets": 243210000.0, "property_plant_equipment": null, "goodwill_intangibles": null, "total_assets": 319480000.0, "accounts_payable": 40950000.0, "short_term_debt": 40030000.0, "current_liabilities": 105310000.0, "long_term_debt": 13120000.0, "total_debt": 79490000.0, "total_liabilities": 122470000.0, "retained_earnings": 112010000.0, "total_equity": 197010000.0}], "cashflow": [{"id": 1994, "security_id": 451, "period": "annual", "fiscal_date": "2026-03-31", "reported_currency": "PKR", "operating_cash_flow": 614220000.0, "capital_expenditure": -3500000.0, "free_cash_flow": 610720000.0, "investing_cash_flow": -109350000.0, "financing_cash_flow": 25080000.0, "dividends_paid": -13050000.0, "stock_repurchase": null, "net_change_in_cash": 529940000.0}, {"id": 1995, "security_id": 451, "period": "annual", "fiscal_date": "2025-03-31", "reported_currency": "PKR", "operating_cash_flow": 350760000.0, "capital_expenditure": -176470000.0, "free_cash_flow": 174290000.0, "investing_cash_flow": -358510000.0, "financing_cash_flow": -74540000.0, "dividends_paid": -29930000.0, "stock_repurchase": null, "net_change_in_cash": -82290000.0}, {"id": 1996, "security_id": 451, "period": "annual", "fiscal_date": "2024-03-31", "reported_currency": "PKR", "operating_cash_flow": 88000000.0, "capital_expenditure": -92050000.0, "free_cash_flow": -4050000.0, "investing_cash_flow": -330680000.0, "financing_cash_flow": 330740000.0, "dividends_paid": -11920000.0, "stock_repurchase": null, "net_change_in_cash": 88050000.0}, {"id": 1997, "security_id": 451, "period": "annual", "fiscal_date": "2023-03-31", "reported_currency": "PKR", "operating_cash_flow": -8130000.0, "capital_expenditure": -2230000.0, "free_cash_flow": -10360000.0, "investing_cash_flow": 16990000.0, "financing_cash_flow": -26080000.0, "dividends_paid": null, "stock_repurchase": null, "net_change_in_cash": -17210000.0}]}, "patterns": [], "score_history": [{"as_of": "2026-07-24", "composite": 70.32, "fundamental": 66.67, "technical": null, "momentum": null, "quality": 64.02, "risk": 89.38}], "dividends": [], "estimates": [], "peers": [], "news": [], "insider": [], "insider_summary": null, "ai_summary": "SYM scores 70/100 overall \u2014 a strong composite profile. Key metrics: ROE 11.5%, net margin 22.6%, debt/equity 0.23, revenue growth 0.8%. Current signal: Buy (confidence 45%). This summary is generated from computed metrics only; it is not investment advice."}